eyadseif123/__init__.py
eyadseif123/_main_.py
eyadseif123/main.py
eyadseif123-0.3.dist-info/METADATA
eyadseif123-0.3.dist-info/WHEEL
eyadseif123-0.3.dist-info/entry_points.txt
eyadseif123-0.3.dist-info/top_level.txt
eyadseif123-0.3.dist-info/RECORD
