Metadata-Version: 2.4
Name: eyadseif123
Version: 0.3
Requires-Dist: flask
Dynamic: requires-dist
